{
  "interfaces": {
    "access": [
      {
        "address": "10.31.31.2",
        "address-iter": "0.0.0.1",
        "gateway": "10.31.31.1",
        "interface": "ens16.30",
        "ipv6": false,
        "stream-group-id": 30,
        "type": "ipoe",
        "vlan-mode": "N:1"
      }
    ],
    "network": [
      {
        "address": "10.32.32.2/24",
        "gateway": "10.32.32.1",
        "interface": "ens17.30"
      }
    ]
  },
  "sessions": {
    "count": 1
  },
  "streams": [
    {
      "direction": "both",
      "length": 1000,
      "name": "L3VPN_30",
      "network-interface": "ens17.30",
      "pps": 1,
      "priority": 72,
      "stream-group-id": 30,
      "type": "ipv4",
      "vlan-priority": 3
    }
  ]
}